{
  "state": "GA",
  "stateName": "Georgia",
  "classifiedAt": "2026-04-09T08:50:21.860Z",
  "total": 12,
  "typeSummary": {
    "benefit": 8,
    "resource": 3,
    "employment": 1
  },
  "scopeSummary": {
    "state": 4,
    "local": 1,
    "federal": 7
  },
  "complexitySummary": {
    "deep": 8,
    "simple": 3,
    "medium": 1
  },
  "programs": [
    {
      "name": "Georgia Medicaid",
      "programType": "benefit",
      "geographicScope": {
        "type": "state",
        "stateVariation": false,
        "localEntities": [
          {
            "name": "Local Department of Family & Children Services (DFCS) offices statewide",
            "type": "service-area"
          }
        ]
      },
      "complexity": "deep",
      "recommendedSections": [
        "prose",
        "what-counts",
        "tier-comparison",
        "documents",
        "county-directory",
        "callout"
      ],
      "signals": {
        "benefitType": "service",
        "hasIncomeTiers": false,
        "hasAssetLimits": true,
        "hasRegionalVariation": true,
        "hasFunctionalReq": true,
        "hasMultipleTiers": true,
        "isStatewide": true
      }
    },
    {
      "name": "Community Care Services Program (CCSP) and SOURCE Waiver",
      "programType": "benefit",
      "geographicScope": {
        "type": "state",
        "stateVariation": false,
        "localEntities": [
          {
            "name": "Local Area Agency on Aging (AAA), county DFCS offices[3][8]",
            "type": "service-area"
          }
        ]
      },
      "complexity": "deep",
      "recommendedSections": [
        "prose",
        "income-table",
        "what-counts",
        "tier-comparison",
        "documents",
        "county-directory",
        "callout"
      ],
      "signals": {
        "benefitType": "service",
        "hasIncomeTiers": true,
        "hasAssetLimits": true,
        "hasRegionalVariation": true,
        "hasFunctionalReq": true,
        "hasMultipleTiers": true,
        "isStatewide": true
      }
    },
    {
      "name": "Georgia PACE (Program of All-Inclusive Care for the Elderly)",
      "programType": "benefit",
      "geographicScope": {
        "type": "local",
        "stateVariation": false,
        "localEntities": [
          {
            "name": "Provider-specific centers (e.g., InnovAge or others post-RFP); check DCH for current locations. No exhaustive list in results.[8][9]",
            "type": "service-area"
          }
        ]
      },
      "complexity": "deep",
      "recommendedSections": [
        "prose",
        "what-counts",
        "documents",
        "county-directory",
        "callout"
      ],
      "signals": {
        "benefitType": "service",
        "hasIncomeTiers": false,
        "hasAssetLimits": true,
        "hasRegionalVariation": true,
        "hasFunctionalReq": true,
        "hasMultipleTiers": false,
        "isStatewide": false
      }
    },
    {
      "name": "Georgia SHIP (State Health Insurance Assistance Program)",
      "programType": "resource",
      "geographicScope": {
        "type": "federal",
        "stateVariation": true,
        "localEntities": [
          {
            "name": "Administered by Georgia Department of Human Services Division of Aging Services; local via area agencies on aging and community partners[2][5]",
            "type": "service-area"
          }
        ]
      },
      "complexity": "simple",
      "recommendedSections": [
        "prose",
        "county-directory"
      ],
      "signals": {
        "benefitType": "service",
        "hasIncomeTiers": false,
        "hasAssetLimits": true,
        "hasRegionalVariation": true,
        "hasFunctionalReq": false,
        "hasMultipleTiers": true,
        "isStatewide": true
      }
    },
    {
      "name": "Senior SNAP (Senior Supplemental Nutrition Assistance Program)",
      "programType": "benefit",
      "geographicScope": {
        "type": "federal",
        "stateVariation": true,
        "localEntities": [
          {
            "name": "Administered statewide by Georgia Division of Family & Children Services (DFCS)",
            "type": "service-area"
          }
        ]
      },
      "complexity": "medium",
      "recommendedSections": [
        "prose",
        "income-table",
        "what-counts",
        "documents",
        "county-directory"
      ],
      "signals": {
        "benefitType": "financial",
        "hasIncomeTiers": true,
        "hasAssetLimits": true,
        "hasRegionalVariation": false,
        "hasFunctionalReq": false,
        "hasMultipleTiers": false,
        "isStatewide": true
      }
    },
    {
      "name": "Georgia LIHEAP (Low Income Home Energy Assistance Program)",
      "programType": "benefit",
      "geographicScope": {
        "type": "federal",
        "stateVariation": true,
        "localEntities": [
          {
            "name": "Local Community Action Agencies (e.g., CAFI, FACAA, SWGACAC); find via county-specific sites or dfcs.georgia.gov.[1][4][5]",
            "type": "service-area"
          }
        ]
      },
      "complexity": "deep",
      "recommendedSections": [
        "prose",
        "income-table",
        "what-counts",
        "documents",
        "county-directory",
        "callout"
      ],
      "signals": {
        "benefitType": "financial",
        "hasIncomeTiers": true,
        "hasAssetLimits": true,
        "hasRegionalVariation": true,
        "hasFunctionalReq": false,
        "hasMultipleTiers": false,
        "isStatewide": true
      }
    },
    {
      "name": "Georgia Weatherization Assistance Program",
      "programType": "benefit",
      "geographicScope": {
        "type": "federal",
        "stateVariation": true,
        "localEntities": [
          {
            "name": "County-specific list at gefa.georgia.gov/how-do-i-apply-weatherization (primary state source).[4]",
            "type": "service-area"
          }
        ]
      },
      "complexity": "deep",
      "recommendedSections": [
        "prose",
        "income-table",
        "what-counts",
        "tier-comparison",
        "documents",
        "county-directory",
        "callout"
      ],
      "signals": {
        "benefitType": "service",
        "hasIncomeTiers": true,
        "hasAssetLimits": true,
        "hasRegionalVariation": true,
        "hasFunctionalReq": false,
        "hasMultipleTiers": true,
        "isStatewide": true
      }
    },
    {
      "name": "Georgia Meals on Wheels (Home-Delivered Meals via HCBS/CCSP)",
      "programType": "benefit",
      "geographicScope": {
        "type": "federal",
        "stateVariation": true,
        "localEntities": [
          {
            "name": "12 AAAs statewide; examples: Cobb County MOW, Senior Services North Fulton, Meals on Wheels Atlanta.",
            "type": "service-area"
          }
        ]
      },
      "complexity": "deep",
      "recommendedSections": [
        "prose",
        "income-table",
        "what-counts",
        "documents",
        "county-directory",
        "callout"
      ],
      "signals": {
        "benefitType": "service",
        "hasIncomeTiers": true,
        "hasAssetLimits": true,
        "hasRegionalVariation": true,
        "hasFunctionalReq": true,
        "hasMultipleTiers": false,
        "isStatewide": false
      }
    },
    {
      "name": "Georgia Caregiver Support (Respite and Caregiving Programs)",
      "programType": "benefit",
      "geographicScope": {
        "type": "state",
        "stateVariation": false,
        "localEntities": [
          {
            "name": "Area Agencies on Aging (locate via aging.georgia.gov); Georgia Department of Community Health for waivers.",
            "type": "service-area"
          }
        ]
      },
      "complexity": "deep",
      "recommendedSections": [
        "prose",
        "income-table",
        "what-counts",
        "tier-comparison",
        "documents",
        "county-directory",
        "callout"
      ],
      "signals": {
        "benefitType": "service",
        "hasIncomeTiers": true,
        "hasAssetLimits": true,
        "hasRegionalVariation": true,
        "hasFunctionalReq": false,
        "hasMultipleTiers": true,
        "isStatewide": true
      }
    },
    {
      "name": "Senior Community Service Employment Program (SCSEP)",
      "programType": "employment",
      "geographicScope": {
        "type": "federal",
        "stateVariation": true,
        "localEntities": [
          {
            "name": "Legacy Link",
            "type": "service-area"
          },
          {
            "name": "AARP Foundation SCSEP",
            "type": "service-area"
          },
          {
            "name": "ACC Aging (Northwest Georgia counties)",
            "type": "service-area"
          },
          {
            "name": "WorkSource Georgia Career Centers",
            "type": "service-area"
          }
        ]
      },
      "complexity": "deep",
      "recommendedSections": [
        "prose",
        "income-table"
      ],
      "signals": {
        "benefitType": "employment",
        "hasIncomeTiers": true,
        "hasAssetLimits": false,
        "hasRegionalVariation": true,
        "hasFunctionalReq": false,
        "hasMultipleTiers": true,
        "isStatewide": false
      }
    },
    {
      "name": "Georgia Legal Assistance for Seniors (Elder Rights & Advocacy)",
      "programType": "resource",
      "geographicScope": {
        "type": "state",
        "stateVariation": false,
        "localEntities": [
          {
            "name": "County-specific law firms via https://aging.georgia.gov/tools-resources/elderly-legal-assistance-program[1]",
            "type": "service-area"
          },
          {
            "name": "Georgia Senior Legal Hotline (statewide): Atlanta Legal Aid[6][8]",
            "type": "service-area"
          },
          {
            "name": "Area Agencies on Aging (12 statewide)[5]",
            "type": "service-area"
          }
        ]
      },
      "complexity": "simple",
      "recommendedSections": [
        "prose",
        "county-directory"
      ],
      "signals": {
        "benefitType": "advocacy",
        "hasIncomeTiers": false,
        "hasAssetLimits": true,
        "hasRegionalVariation": true,
        "hasFunctionalReq": false,
        "hasMultipleTiers": true,
        "isStatewide": true
      }
    },
    {
      "name": "Georgia Long-Term Care Ombudsman Program",
      "programType": "resource",
      "geographicScope": {
        "type": "federal",
        "stateVariation": true,
        "localEntities": [
          {
            "name": "Office of the State Long-Term Care Ombudsman within Georgia Department of Human Services’ Division of Aging Services; local services via AAAs and non-profits[4][6][8]",
            "type": "service-area"
          }
        ]
      },
      "complexity": "simple",
      "recommendedSections": [
        "prose",
        "county-directory"
      ],
      "signals": {
        "benefitType": "advocacy",
        "hasIncomeTiers": false,
        "hasAssetLimits": true,
        "hasRegionalVariation": true,
        "hasFunctionalReq": false,
        "hasMultipleTiers": false,
        "isStatewide": true
      }
    }
  ]
}